{
    "doi": "10.1016/j.matlet.2021.129428",
    "extracted_info": {
        "high entropy alloy formula": "Ti 1.5 ZrNbAl 0.3",
        "microstructure": "disordered BCC structure without precipitation",
        "processing method": "cast in vacuum melting furnace, cold-rolled, annealed at 800 \u00b0C for 1 h and air-cooled, then annealed at 600 \u00b0C for 1 h and water quenched",
        "BCC/FCC/other": "BCC",
        "grain size": 24.4,
        "experimental density": "No information",
        "hardness": "No information",
        "type of test": "tensile",
        "test temperature": "No information",
        "yield strength": 876,
        "ultimate tensile strength": "No information",
        "elongation": 23.0,
        "elongation plastic": "No information",
        "experimental young modulus": "No information",
        "oxygen content": "No information",
        "nitrogen content": "No information",
        "carbon content": "No information"
    }
}