{
    "doi": "10.1139/e73-036",
    "extracted_info": {
        "melt": "mugearite",
        "diffusing species": "calcium",
        "type of experiment": "electron microprobe analysis",
        "test temperature": {
            "min": 1230,
            "max": 1423
        },
        "pressure": "No information",
        "diffusivity": {
            "min": 1.07e-07,
            "max": 3.36e-07
        },
        "SiO2": "No information",
        "TiO2": "No information",
        "Al2O3": "No information",
        "FeOt": "No information",
        "MnO": "No information",
        "MgO": "No information",
        "CaO": {
            "natural glass": "No information",
            "Ca-rich glass": "10 wt. %"
        },
        "Na2O": "No information",
        "K2O": "No information",
        "P2O5": "No information",
        "H2Ot": "No information"
    }
}