{
    "doi": "10.1016/j.actamat.2019.06.032",
    "extracted_info": [
        {
            "high entropy alloy formula": "Al0.4Hf0.6NbTaTiZr",
            "microstructure": "BCC",
            "processing method": "HIP+A",
            "BCC/FCC/other": "BCC",
            "grain size": "No information",
            "experimental density": 9.08,
            "hardness": "No information",
            "type of test": "Compression",
            "test temperature": 23,
            "yield strength": 1841,
            "ultimate tensile strength": "No information",
            "elongation": "No information",
            "elongation plastic": "No information",
            "experimental young modulus": "No information",
            "oxygen content": "No information",
            "nitrogen content": "No information",
            "carbon content": "No information"
        },
        {
            "high entropy alloy formula": "HfMo0.5NbTiV0.5",
            "microstructure": "BCC",
            "processing method": "AC",
            "BCC/FCC/other": "BCC",
            "grain size": "No information",
            "experimental density": 8.96,
            "hardness": "No information",
            "type of test": "Compression",
            "test temperature": 23,
            "yield strength": 1260,
            "ultimate tensile strength": "No information",
            "elongation": "No information",
            "elongation plastic": "No information",
            "experimental young modulus": "No information",
            "oxygen content": "No information",
            "nitrogen content": "No information",
            "carbon content": "No information"
        },
        {
            "high entropy alloy formula": "HfMoNbTaTiZr",
            "microstructure": "BCC",
            "processing method": "AC",
            "BCC/FCC/other": "BCC",
            "grain size": "No information",
            "experimental density": 9.93,
            "hardness": "No information",
            "type of test": "Compression",
            "test temperature": 23,
            "yield strength": 1512,
            "ultimate tensile strength": "No information",
            "elongation": "No information",
            "elongation plastic": "No information",
            "experimental young modulus": "No information",
            "oxygen content": "No information",
            "nitrogen content": "No information",
            "carbon content": "No information"
        },
        {
            "high entropy alloy formula": "HfMoTaTiZr",
            "microstructure": "BCC",
            "processing method": "AC",
            "BCC/FCC/other": "BCC",
            "grain size": "No information",
            "experimental density": 10.18,
            "hardness": "No information",
            "type of test": "Compression",
            "test temperature": 23,
            "yield strength": 1600,
            "ultimate tensile strength": "No information",
            "elongation": "No information",
            "elongation plastic": "No information",
            "experimental young modulus": "No information",
            "oxygen content": "No information",
            "nitrogen content": "No information",
            "carbon content": "No information"
        },
        {
            "high entropy alloy formula": "AlCrMoNbTi",
            "microstructure": "BCC+Laves",
            "processing method": "A",
            "BCC/FCC/other": "other",
            "grain size": "No information",
            "experimental density": 6.56,
            "hardness": "No information",
            "type of test": "Compression",
            "test temperature": 23,
            "yield strength": 1010,
            "ultimate tensile strength": "No information",
            "elongation": "No information",
            "elongation plastic": "No information",
            "experimental young modulus": "No information",
            "oxygen content": "No information",
            "nitrogen content": "No information",
            "carbon content": "No information"
        },
        {
            "high entropy alloy formula": "Al0.24NbTiVZr",
            "microstructure": "BCC+Laves",
            "processing method": "HIP+A",
            "BCC/FCC/other": "other",
            "grain size": "No information",
            "experimental density": 6.34,
            "hardness": "No information",
            "type of test": "Compression",
            "test temperature": 23,
            "yield strength": 1240,
            "ultimate tensile strength": "No information",
            "elongation": "No information",
            "elongation plastic": "No information",
            "experimental young modulus": "No information",
            "oxygen content": "No information",
            "nitrogen content": "No information",
            "carbon content": "No information"
        },
        {
            "high entropy alloy formula": "HfMo0.5NbSi0.5TiV0.5",
            "microstructure": "BCC+M5Si3",
            "processing method": "AC",
            "BCC/FCC/other": "other",
            "grain size": "No information",
            "experimental density": 8.16,
            "hardness": "No information",
            "type of test": "Compression",
            "test temperature": 23,
            "yield strength": 1787,
            "ultimate tensile strength": "No information",
            "elongation": "No information",
            "elongation plastic": "No information",
            "experimental young modulus": "No information",
            "oxygen content": "No information",
            "nitrogen content": "No information",
            "carbon content": "No information"
        },
        {
            "high entropy alloy formula": "MoNbTaTiVW",
            "microstructure": "BCC",
            "processing method": "AC",
            "BCC/FCC/other": "BCC",
            "grain size": "No information",
            "experimental density": 10.91,
            "hardness": "No information",
            "type of test": "Compression",
            "test temperature": 23,
            "yield strength": 1515,
            "ultimate tensile strength": "No information",
            "elongation": "No information",
            "elongation plastic": "No information",
            "experimental young modulus": "No information",
            "oxygen content": "No information",
            "nitrogen content": "No information",
            "carbon content": "No information"
        },
        {
            "high entropy alloy formula": "MoNbTaTiW",
            "microstructure": "BCC",
            "processing method": "AC",
            "BCC/FCC/other": "BCC",
            "grain size": "No information",
            "experimental density": 11.72,
            "hardness": "No information",
            "type of test": "Compression",
            "test temperature": 23,
            "yield strength": 1343,
            "ultimate tensile strength": "No information",
            "elongation": "No information",
            "elongation plastic": "No information",
            "experimental young modulus": "No information",
            "oxygen content": "No information",
            "nitrogen content": "No information",
            "carbon content": "No information"
        },
        {
            "high entropy alloy formula": "MoNbTaW",
            "microstructure": "BCC",
            "processing method": "HIP+A",
            "BCC/FCC/other": "BCC",
            "grain size": "No information",
            "experimental density": 13.6,
            "hardness": "No information",
            "type of test": "Compression",
            "test temperature": 23,
            "yield strength": 996,
            "ultimate tensile strength": "No information",
            "elongation": "No information",
            "elongation plastic": "No information",
            "experimental young modulus": "No information",
            "oxygen content": "No information",
            "nitrogen content": "No information",
            "carbon content": "No information"
        },
        {
            "high entropy alloy formula": "MoNbTaVW",
            "microstructure": "BCC",
            "processing method": "HIP+A",
            "BCC/FCC/other": "BCC",
            "grain size": "No information",
            "experimental density": 12.29,
            "hardness": "No information",
            "type of test": "Compression",
            "test temperature": 23,
            "yield strength": 1246,
            "ultimate tensile strength": "No information",
            "elongation": "No information",
            "elongation plastic": "No information",
            "experimental young modulus": "No information",
            "oxygen content": "No information",
            "nitrogen content": "No information",
            "carbon content": "No information"
        },
        {
            "high entropy alloy formula": "NbTa0.3TiZr",
            "microstructure": "BCC",
            "processing method": "HIP+A",
            "BCC/FCC/other": "BCC",
            "grain size": "No information",
            "experimental density": 7.81,
            "hardness": "No information",
            "type of test": "Compression",
            "test temperature": 23,
            "yield strength": 882,
            "ultimate tensile strength": "No information",
            "elongation": "No information",
            "elongation plastic": "No information",
            "experimental young modulus": "No information",
            "oxygen content": "No information",
            "nitrogen content": "No information",
            "carbon content": "No information"
        },
        {
            "high entropy alloy formula": "NbTiZr",
            "microstructure": "BCC",
            "processing method": "HIP+A",
            "BCC/FCC/other": "BCC",
            "grain size": "No information",
            "experimental density": 6.63,
            "hardness": "No information",
            "type of test": "Compression",
            "test temperature": 23,
            "yield strength": 975,
            "ultimate tensile strength": "No information",
            "elongation": "No information",
            "elongation plastic": "No information",
            "experimental young modulus": "No information",
            "oxygen content": "No information",
            "nitrogen content": "No information",
            "carbon content": "No information"
        }
    ]
}