{
    "doi": "10.1080/21663831.2016.1221861",
    "extracted_info": [
        {
            "high entropy alloy formula": "Ti35Zr27.5Hf27.5Nb5Ta5",
            "microstructure": "BCC",
            "processing method": "COLD ROLL & SOLUTION TREATMENT",
            "BCC/FCC/other": "BCC",
            "grain size": 40.0,
            "experimental density": "No information",
            "hardness": "No information",
            "type of test": "TENSILE",
            "test temperature": "No information",
            "yield strength": 540.0,
            "ultimate tensile strength": "No information",
            "elongation": "No information",
            "elongation plastic": "No information",
            "experimental young modulus": "No information",
            "oxygen content": "No information",
            "nitrogen content": "No information",
            "carbon content": "No information"
        },
        {
            "high entropy alloy formula": "Ti20Zr20Hf20Nb20Ta20",
            "microstructure": "No information",
            "processing method": "No information",
            "BCC/FCC/other": "No information",
            "grain size": "No information",
            "experimental density": "No information",
            "hardness": "No information",
            "type of test": "No information",
            "test temperature": "No information",
            "yield strength": "No information",
            "ultimate tensile strength": "No information",
            "elongation": "No information",
            "elongation plastic": "No information",
            "experimental young modulus": "No information",
            "oxygen content": "No information",
            "nitrogen content": "No information",
            "carbon content": "No information"
        }
    ]
}